pynviread/__init__.py
pynviread/_version.py
pynviread/reader.py
pynviread/subprocess_calls.py
pynviread/examples/__init__.py
pynviread/examples/cockatoo.mp4
pynviread/examples/cockatoo_yuv420p.mp4
test/__init__.py
test/testNvidiaReader.py
pynviread-0.2.dist-info/METADATA
pynviread-0.2.dist-info/WHEEL
pynviread-0.2.dist-info/top_level.txt
pynviread-0.2.dist-info/RECORD
